clingox/__init__.py
clingox/ast.py
clingox/backend.py
clingox/pprint.py
clingox/program.py
clingox/py.typed
clingox/reify.py
clingox/solving.py
clingox/theory.py
clingox/testing/__init__.py
clingox/testing/ast.py
clingox-1.2.1.dist-info/LICENSE
clingox-1.2.1.dist-info/METADATA
clingox-1.2.1.dist-info/WHEEL
clingox-1.2.1.dist-info/top_level.txt
clingox-1.2.1.dist-info/RECORD
