Metadata-Version: 2.1
Name: clingox
Version: 1.2.1
Summary: Support library for clingo.
Home-page: https://github.com/potassco/python-clingox
Author: Roland Kaminski
Author-email: kaminski@cs.uni-potsdam.de
License: MIT
Requires-Python: >=3.7
License-File: LICENSE
Requires-Dist: clingo>=5.5
Requires-Dist: dataclasses; python_version < "3.7"
